fusionctl/__init__.py
fusionctl/cli.py
fusionctl/config.py
fusionctl/manager.py
fusionctl-0.1.3.dist-info/licenses/LICENSE
fusionctl-0.1.3.dist-info/METADATA
fusionctl-0.1.3.dist-info/WHEEL
fusionctl-0.1.3.dist-info/entry_points.txt
fusionctl-0.1.3.dist-info/top_level.txt
fusionctl-0.1.3.dist-info/RECORD
