Metadata-Version: 2.4
Name: fusionctl
Version: 0.1.3
Summary: Manage VMware Fusion VMs from Python or the CLI
Author: pmrsec
License-Expression: MIT
Project-URL: Homepage, https://github.com/pmrsec/fusionctl
Project-URL: Repository, https://github.com/pmrsec/fusionctl
Project-URL: Issues, https://github.com/pmrsec/fusionctl/issues
Keywords: vmware,fusion,vm,vmrun,automation
Classifier: Programming Language :: Python :: 3
Classifier: Operating System :: MacOS
Requires-Python: >=3.10
License-File: LICENSE
Dynamic: license-file
